Metadata-Version: 2.1
Name: calcarea
Version: 0.1
Summary: Package which claculates area of circle and rectangle
Home-page: https://github.com/SubhashiniRajesh26/PYPI_practice
Author: Subhashini
Author-email: subhashinirajesh25@gmail.com
License: GREEN LIME
License-File: LICENCE.txt
